CConsole/__init__.py
CConsole/console.py
CConsole/enums.py
CConsole/structures.py
cconsole-1.0.0.dist-info/licenses/LICENSE
cconsole-1.0.0.dist-info/METADATA
cconsole-1.0.0.dist-info/WHEEL
cconsole-1.0.0.dist-info/top_level.txt
cconsole-1.0.0.dist-info/RECORD
