Metadata-Version: 2.4
Name: CConsole
Version: 1.0.0
Summary: Cool Console Prompt - Windows console customization library
Author: Xylera
License: MIT
Project-URL: Homepage, https://github.com/Xylera/CConsole
Project-URL: Repository, https://github.com/Xylera/CConsole
Keywords: console,terminal,windows,vt100,ansi,customization
Classifier: Development Status :: 5 - Production/Stable
Classifier: Environment :: Console
Classifier: Intended Audience :: Developers
Classifier: License :: OSI Approved :: MIT License
Classifier: Operating System :: Microsoft :: Windows
Classifier: Programming Language :: Python :: 3
Classifier: Programming Language :: Python :: 3.7
Classifier: Programming Language :: Python :: 3.8
Classifier: Programming Language :: Python :: 3.9
Classifier: Programming Language :: Python :: 3.10
Classifier: Programming Language :: Python :: 3.11
Classifier: Programming Language :: Python :: 3.12
Classifier: Topic :: System :: Console Fonts
Classifier: Topic :: Terminals
Requires-Python: >=3.7
License-File: LICENSE
Dynamic: license-file
Dynamic: requires-python
